typeit/__init__.py
typeit/compat.py
typeit/definitions.py
typeit/flags.py
typeit/interface.py
typeit/utils.py
typeit/cli/__init__.py
typeit/cli/gen.py
typeit/codegen/__init__.py
typeit/combinator/__init__.py
typeit/combinator/combinator.py
typeit/combinator/constructor.py
typeit/custom_types/__init__.py
typeit/custom_types/json_string.py
typeit/parser/__init__.py
typeit/parser/type_info.py
typeit/schema/__init__.py
typeit/schema/errors.py
typeit/schema/meta.py
typeit/schema/nodes.py
typeit/schema/primitives.py
typeit/schema/types.py
typeit/sums/__init__.py
typeit/sums/impl.py
typeit/sums/types.py
typeit/tokenizer/__init__.py
typeit-3.11.1.3.dist-info/LICENSE
typeit-3.11.1.3.dist-info/METADATA
typeit-3.11.1.3.dist-info/WHEEL
typeit-3.11.1.3.dist-info/entry_points.txt
typeit-3.11.1.3.dist-info/top_level.txt
typeit-3.11.1.3.dist-info/RECORD
