Metadata-Version: 2.1
Name: typeit
Version: 3.11.1.3
Summary: typeit brings typed data into your project
Home-page: https://github.com/avanov/typeit
Author: Maxim Avanov
Author-email: maxim.avanov@gmail.com
Keywords: utils typing json yaml serialization deserialization structured-data
Classifier: Development Status :: 5 - Production/Stable
Classifier: Intended Audience :: Developers
Classifier: License :: OSI Approved
Classifier: License :: OSI Approved :: MIT License
Classifier: Programming Language :: Python
Classifier: Programming Language :: Python :: 3
Classifier: Operating System :: POSIX
Provides-Extra: third_party
License-File: LICENSE
